Workbook

Sheet Инструкция
A1: BizQoldau — рабочая книга MVP
A3: Цель | B3: BizQoldau: каталог-навигатор по грантам, субсидиям и льготам для предпринимателей Казахстана (фокус — Алматы). Сайт показывает подходящие программы, а заявку человек подаёт у государства. Стек: Airtable + Softr.
A5: Лист | B5: Что внутри
A6: Программы | B6: Стартовый каталог из открытых источников (сентябрь–октябрь 2026). Синий шрифт — вводимые данные, чёрный — формулы.
A7: Схема Airtable | B7: Поля таблиц Programs и Subscribers.
A8: План запуска | B8: План на 3 часа: часы и статусы редактируются, итоги считаются формулами.
A9: Метрики | B9: Вводите посетителей, подписки, клики; конверсии и статистика каталога считаются автоматически.
A11: Легенда | B11: Синий шрифт = ввод. Чёрный = формула. Жёлтая заливка = ключевое допущение, которое нужно заполнить.
A12: Важно | B12: Условия, суммы и сроки меняются. Перед публикацией сверяйте каждую программу с оператором и Реестром мер государственной поддержки. Программ, специфичных именно для Алматы (акимат, филиал «Даму», Атамекен), в списке мало — их нужно добавить вручную.
A13: Валюта | B13: Все суммы в тенге (₸). МРП — месячный расчётный показатель; по источнику 400 МРП ≈ 1,73 млн ₸ (МРП ≈ 4 325 ₸, допущение, проверьте актуальное значение).

Sheet Программы
A1: Название | B1: Оператор | C1: Тип | D1: Регион | E1: Сфера | F1: Кому подходит / условия | G1: Сумма / параметры | H1: Дедлайн | I1: Источник | J1: Статус | K1: Проверено | L1: Дней до дедлайна | M1: Флаг дедлайна | N1: Ключевые слова | O1: Кратко | P1: Подходит для | Q1: Полное описание | R1: Требования | S1: Документы | T1: Как получить | U1: Официальный сайт | V1: Офиц. сайт проверен? | W1: Название (KK) | X1: Оператор (KK) | Y1: Сумма / параметры (KK) | Z1: Кому подходит / условия (KK) | AA1: Кратко (KK) | AB1: Подходит для (KK) | AC1: Полное описание (KK) | AD1: Требования (KK) | AE1: Документы (KK) | AF1: Как получить (KK) | AG1: Ключевые слова (KK) | AI1: Карточка на сайте: Кратко + Подходит для. Страница «Подробнее»: Полное описание, Требования, Документы, Как получить, кнопка на «Официальный сайт». Колонки «(KK)» — казахская версия; если поле пустое, сайт покажет русский текст. Переводы требуют проверки носителем языка.
A2: Грант на реализацию новых бизнес-идей | B2: Региональные операторы конкурса | C2: Грант | D2: Вся РК | E2: Все сферы | F2: Безработные и ИП до 1 года из установленных социальных категорий; нужны обучение «Бастау Бизнес», бизнес-план, конкурсный отбор | G2: до 400 МРП (≈1,73 млн ₸) | I2: https://finance.kz/articles/gosudarstvennye-programmy-podderzhki-predprinimateley | J2: Опубликовано | K2: 46299 | L2: =IF(OR(A2="",H2=""),"",H2-TODAY()) | M2: =IF(A2="","",IF(H2="","Уточняйте",IF(L2<0,"Истёк",IF(L2<=30,"Скоро дедлайн","Открыто")))) -> Уточняйте | N2: кофейня кафе салон красоты магазин старт открытие начинающий | O2: Безвозмездный грант на запуск стартового бизнеса. Предоставляется однократно по итогам конкурса. | P2: • Безработные • ИП до 1 года (из установленных социальных категорий) • Начинающие предприниматели | Q2: Государственный грант для запуска и реализации стартового бизнеса. При соблюдении условий предоставляется безвозмездно и безвозвратно, один раз. В 2026 году региональные объявления о приёме заявок указывали размер 400 МРП — 1,73 млн ₸. | R2: • Принадлежность к установленным социальным категориям • Статус зарегистрированного безработного или ИП не более 1 года • Обучение основам предпринимательства «Бастау Бизнес» (в отдельных случаях обязательно) • Бизнес-план • Участие в конкурсном отборе | S2: • Удостоверение личности • Бизнес-план • Сертификат обучения «Бастау Бизнес» (если требуется) • Подтверждение социальной категории • Регистрационные документы ИП (если есть) | T2: 1. Определите бизнес-идею и проверьте, входите ли вы в одну из категорий получателей. 2. Пройдите обучение «Бастау Бизнес», если оно требуется. 3. Подготовьте бизнес-план. 4. Дождитесь объявления о приёме заявок в вашем регионе и подайте документы через указанный канал. | U2: https://finance.kz/articles/gosudarstvennye-programmy-podderzhki-predprinimateley | V2: Нет — добавить | W2: Жаңа бизнес-идеяларды іске асыруға арналған грант | X2: Конкурстың өңірлік операторлары | Y2: 400 АЕК-ге дейін (≈1,73 млн ₸) | Z2: Белгіленген әлеуметтік санаттардағы жұмыссыздар және 1 жылға дейінгі ЖК; «Бастау Бизнес» оқытуы, бизнес-жоспар, конкурстық іріктеу қажет | AA2: Бастапқы бизнесті бастауға арналған қайтарымсыз грант. Конкурс қорытындысы бойынша бір рет беріледі. | AB2: • Жұмыссыздар • Белгіленген әлеуметтік санаттағы 1 жылға дейінгі ЖК • Бастаушы кәсіпкерлер | AC2: Бастапқы бизнесті бастау және іске асыру үшін мемлекеттік грант. Шарттар сақталған жағдайда қайтарымсыз және қайтарусыз беріледі, бір рет. 2026 жылы өңірлердегі өтінім қабылдау туралы хабарландыруларда мөлшері 400 АЕК — 1,73 млн ₸ деп көрсетілген. | AD2: • Белгіленген әлеуметтік санаттарға жату • Тіркелген жұмыссыз немесе 1 жылдан аспайтын ЖК мәртебесі • «Бастау Бизнес» кәсіпкерлік негіздеріне оқыту (кейбір жағдайларда міндетті) • Бизнес-жоспар • Конкурстық іріктеуге қатысу | AE2: • Жеке куәлік • Бизнес-жоспар • «Бастау Бизнес» оқу сертификаты (қажет болса) • Әлеуметтік санатты растау • ЖК тіркеу құжаттары (болса) | AF2: 1. Бизнес-идеяны анықтап, алушылар санаттарының біріне жататыныңызды тексеріңіз. 2. Қажет болса, «Бастау Бизнес» оқуынан өтіңіз. 3. Бизнес-жоспарды дайындаңыз. 4. Өңіріңізде өтінім қабылдау туралы хабарландыруды күтіп, көрсетілген арна арқылы құжаттарды тапсырыңыз. | AG2: кофехана кафе сұлулық салоны дүкен бастау ашу бастаушы жұмыссыз
A3: Грант для социального предпринимательства | B3: Реестр мер господдержки | C3: Грант | D3: Вся РК | E3: Социальное предпринимательство | F3: Субъекты социального предпринимательства; софинансирование, рабочие места, инвестплан | G3: до 5 млн ₸ | I3: https://finance.kz/articles/gosudarstvennye-programmy-podderzhki-predprinimateley | J3: Опубликовано | K3: 46299 | L3: =IF(OR(A3="",H3=""),"",H3-TODAY()) | M3: =IF(A3="","",IF(H3="","Уточняйте",IF(L3<0,"Истёк",IF(L3<=30,"Скоро дедлайн","Открыто")))) -> Уточняйте | N3: социальный инвалиды | O3: Грант на новые бизнес-идеи для субъектов социального предпринимательства. | P3: • Субъекты социального предпринимательства • ИП • ТОО | Q3: Мера из официального Реестра: государственные гранты для реализации новых бизнес-идей субъектами социального предпринимательства. Размер — до 5 млн ₸, предусмотрены условия софинансирования и создания рабочих мест. | R3: • Подтверждённый статус субъекта социального предпринимательства • Софинансирование проекта • Создание рабочих мест • Инвестиционный план | S3: • Удостоверение личности • Регистрационные документы ИП или ТОО • Бизнес-план и финансовые расчёты • Сведения о проекте и документы на приобретаемое имущество • Документы по залогу (если требуются) • Подтверждение соответствия категории получателя | T3: 1. Сначала подтвердите, что ваш бизнес относится к социальному предпринимательству. 2. Подготовьте документы. 3. Подайте заявку тем способом, который указан оператором (зависит от меры и региона). 4. Дождитесь решения. При отказе узнайте причину и возможность повторной подачи. | U3: https://finance.kz/articles/gosudarstvennye-programmy-podderzhki-predprinimateley | V3: Нет — добавить | W3: Әлеуметтік кәсіпкерлікке арналған грант | X3: Мемлекеттік қолдау шараларының тізілімі | Y3: 5 млн ₸-ге дейін | Z3: Әлеуметтік кәсіпкерлік субъектілері; бірлесіп қаржыландыру, жұмыс орындары, инвестициялық жоспар | AA3: Әлеуметтік кәсіпкерлік субъектілеріне жаңа бизнес-идеяларға арналған грант. | AB3: • Әлеуметтік кәсіпкерлік субъектілері • ЖК • ЖШС | AC3: Ресми Тізілімдегі шара: әлеуметтік кәсіпкерлік субъектілерінің жаңа бизнес-идеяларын іске асыруға арналған мемлекеттік гранттар. Мөлшері — 5 млн ₸-ге дейін, бірлесіп қаржыландыру және жұмыс орындарын құру шарттары көзделген. | AD3: • Әлеуметтік кәсіпкерлік субъектісінің расталған мәртебесі • Жобаны бірлесіп қаржыландыру • Жұмыс орындарын құру • Инвестициялық жоспар | AE3: • Жеке куәлік • ЖК немесе ЖШС тіркеу құжаттары • Бизнес-жоспар және қаржылық есептеулер • Жоба туралы мәліметтер және сатып алынатын мүлікке құжаттар • Кепіл құжаттары (қажет болса) • Алушы санатына сәйкестікті растау | AF3: 1. Алдымен бизнесіңіздің әлеуметтік кәсіпкерлікке жататынын растаңыз. 2. Құжаттарды дайындаңыз. 3. Өтінімді оператор көрсеткен тәсілмен беріңіз (шара мен өңірге байланысты). 4. Шешімді күтіңіз. Бас тартылған жағдайда себебін және қайта өтінім беру мүмкіндігін біліңіз. | AG3: әлеуметтік мүгедек көпбалалы
A4: «Бастау Бизнес» — обучение для начинающих | B4: Программа обучения | C4: Обучение | D4: Вся РК | E4: Все сферы | F4: Начинающие; сертификат может быть условием гранта | G4: обучение | I4: https://finance.kz/articles/gosudarstvennye-programmy-podderzhki-predprinimateley | J4: Опубликовано | K4: 46299 | L4: =IF(OR(A4="",H4=""),"",H4-TODAY()) | M4: =IF(A4="","",IF(H4="","Уточняйте",IF(L4<0,"Истёк",IF(L4<=30,"Скоро дедлайн","Открыто")))) -> Уточняйте | N4: курсы начинающий старт | O4: Обучение основам предпринимательства. Сертификат может быть условием участия в грантовом конкурсе. | P4: • Начинающие предприниматели • Планирующие открыть дело | Q4: Проект связан с обучением основам предпринимательства. Для отдельных механизмов поддержки наличие сертификата — одно из условий участия в конкурсе на грант. | R4: • Условия набора и категории участников уточняйте у оператора обучения | S4: • Удостоверение личности • Другие документы — по требованию оператора | T4: 1. Узнайте у оператора ближайший набор. 2. Пройдите обучение и получите сертификат. 3. Используйте сертификат при подаче на грант, если он требуется. | U4: https://finance.kz/articles/gosudarstvennye-programmy-podderzhki-predprinimateley | V4: Нет — добавить | W4: «Бастау Бизнес» — бастаушыларға арналған оқыту | X4: Кәсіпкерлерді оқыту бағдарламасы | Y4: оқыту | Z4: Бастаушылар; сертификат грант шарты болуы мүмкін | AA4: Кәсіпкерлік негіздеріне оқыту. Сертификат гранттық конкурсқа қатысу шарты болуы мүмкін. | AB4: • Бастаушы кәсіпкерлер • Іс ашуды жоспарлап жүргендер | AC4: Жоба кәсіпкерлік негіздеріне оқытумен байланысты. Қолдаудың кейбір тетіктері үшін сертификаттың болуы грантқа конкурсқа қатысу шарттарының бірі болып табылады. | AD4: • Іріктеу шарттары мен қатысушылар санаттарын оқыту операторынан нақтылаңыз | AE4: • Жеке куәлік • Басқа құжаттар — оператордың талабы бойынша | AF4: 1. Оператордан жақын арадағы қабылдау мерзімін біліңіз. 2. Оқудан өтіп, сертификат алыңыз. 3. Қажет болса, грантқа өтінім бергенде сертификатты пайдаланыңыз. | AG4: курс оқыту бастаушы бастау
A5: Субсидирование ставки по кредиту | B5: Фонд «Даму» | C5: Субсидия ставки | D5: Вся РК | E5: Производство | F5: Производство, логистика, инновации (по обзорам); проверьте перечень видов деятельности | G5: ставка для заёмщика ориентировочно 7–9% | I5: https://finance.kz/articles/gosudarstvennye-programmy-podderzhki-predprinimateley | J5: Опубликовано | K5: 46299 | L5: =IF(OR(A5="",H5=""),"",H5-TODAY()) | M5: =IF(A5="","",IF(H5="","Уточняйте",IF(L5<0,"Истёк",IF(L5<=30,"Скоро дедлайн","Открыто")))) -> Уточняйте | N5: кредит процент ставка оборудование логистика | O5: Государство компенсирует часть процента по кредиту коммерческого банка. | P5: • ИП • Малый и средний бизнес • Производственные, логистические и инновационные проекты | Q5: Субсидирование снижает стоимость кредита: часть стоимости финансирования компенсирует государство. По обзору, конечная ставка для заёмщика составляет от 7% до 9% годовых для производственных, логистических и инновационных предприятий. Сумма, срок субсидирования и условия зависят от конкретной программы. | R5: • Вид деятельности входит в допустимый перечень программы • Соответствие категории предпринимателя • Соответствие проекта требованиям программы | S5: • Удостоверение личности • Регистрационные документы ИП или ТОО • Бизнес-план и финансовые расчёты • Сведения о проекте и документы на приобретаемое имущество • Документы по залогу (если требуются) • Подтверждение соответствия категории получателя | T5: 1. Выберите программу субсидирования, подходящую вашей цели (инвестиции или оборотные средства). 2. Проверьте, подходит ли вам программа: статус ИП/ТОО, регион, вид деятельности (ОКЭД), цель финансирования. 3. Подготовьте документы. 4. Подайте заявку тем способом, который указан оператором (зависит от меры и региона). 5. Дождитесь решения. При отказе узнайте причину и возможность повторной подачи. | U5: https://damu.kz | V5: Да | W5: Несие бойынша мөлшерлемені субсидиялау | X5: «Даму» кәсіпкерлікті дамыту қоры | Y5: қарыз алушы үшін мөлшерлеме шамамен 7–9% | Z5: Өндіріс, логистика, инновациялар (шолулар бойынша); қызмет түрлерінің тізімін тексеріңіз | AA5: Мемлекет коммерциялық банк несиесі бойынша пайыздың бір бөлігін өтейді. | AB5: • ЖК • Шағын және орта бизнес • Өндірістік, логистикалық және инновациялық жобалар | AC5: Субсидиялау несие құнын төмендетеді: қаржыландыру құнының бір бөлігін мемлекет өтейді. Шолу бойынша қарыз алушы үшін түпкілікті мөлшерлеме өндірістік, логистикалық және инновациялық кәсіпорындар үшін жылдық 7%-дан 9%-ға дейін құрайды. Сома, субсидиялау мерзімі және шарттар нақты бағдарламаға байланысты. | AD5: • Қызмет түрі бағдарламаның рұқсат етілген тізіміне кіреді • Кәсіпкер санатына сәйкестік • Жобаның бағдарлама талаптарына сәйкестігі | AE5: • Жеке куәлік • ЖК немесе ЖШС тіркеу құжаттары • Бизнес-жоспар және қаржылық есептеулер • Жоба туралы мәліметтер және сатып алынатын мүлікке құжаттар • Кепіл құжаттары (қажет болса) • Алушы санатына сәйкестікті растау | AF5: 1. Мақсатыңызға (инвестиция немесе айналым қаражаты) сәйкес субсидиялау бағдарламасын таңдаңыз. 2. Бағдарламаның сізге сәйкес келетінін тексеріңіз: ЖК/ЖШС мәртебесі, өңір, қызмет түрі (ЭҚЖЖ), қаржыландыру мақсаты. 3. Құжаттарды дайындаңыз. 4. Өтінімді оператор көрсеткен тәсілмен беріңіз (шара мен өңірге байланысты). 5. Шешімді күтіңіз. Бас тартылған жағдайда себебін және қайта өтінім беру мүмкіндігін біліңіз. | AG5: несие пайыз мөлшерлеме жабдық логистика өндіріс
A6: Гарантия по кредиту, если не хватает залога | B6: Фонд «Даму» | C6: Гарантия | D6: Вся РК | E6: Все сферы | F6: Малый и микробизнес с недостатком залога | G6: до 85% суммы кредита (по отдельным механизмам) | I6: https://finance.kz/articles/gosudarstvennye-programmy-podderzhki-predprinimateley | J6: Опубликовано | K6: 46299 | L6: =IF(OR(A6="",H6=""),"",H6-TODAY()) | M6: =IF(A6="","",IF(H6="","Уточняйте",IF(L6<0,"Истёк",IF(L6<=30,"Скоро дедлайн","Открыто")))) -> Уточняйте | N6: залог кредит банк кофейня магазин салон | O6: Гарантия фонда помогает получить кредит в банке при недостатке собственного залога. | P6: • Малый и микробизнес • ИП • ТОО | Q6: Гарантирование помогает обеспечить обязательства перед банком при недостатке залога. По отдельным механизмам Реестра размер гарантии достигает 85% суммы кредита (например, для некоторых кредитов малого и микробизнеса). Это не «кредит без залога», а гарантия на часть суммы. | R6: • Недостаточное собственное залоговое обеспечение • Соответствие условиям конкретного механизма гарантирования • Одобрение финансирования финансовой организацией | S6: • Удостоверение личности • Регистрационные документы ИП или ТОО • Бизнес-план и финансовые расчёты • Сведения о проекте и документы на приобретаемое имущество • Документы по залогу (если требуются) • Подтверждение соответствия категории получателя | T6: 1. Обратитесь в банк-партнёр или к оператору и уточните, доступна ли гарантия для вашего кредита. 2. Подготовьте документы. 3. Подайте заявку тем способом, который указан оператором (зависит от меры и региона). 4. Дождитесь решения. При отказе узнайте причину и возможность повторной подачи. | U6: https://damu.kz | V6: Да | W6: Кепіл жеткіліксіз болса, несие бойынша кепілдік | X6: «Даму» қоры | Y6: несие сомасының 85%-ына дейін (жекелеген тетіктер бойынша) | Z6: Кепілі жеткіліксіз шағын және микробизнес | AA6: Қор кепілдігі жеке кепіл жеткіліксіз болғанда банктен несие алуға көмектеседі. | AB6: • Шағын және микробизнес • ЖК • ЖШС | AC6: Кепілдік беру кепіл жеткіліксіз болғанда банк алдындағы міндеттемелерді қамтамасыз етуге көмектеседі. Тізілімнің жекелеген тетіктері бойынша кепілдік мөлшері несие сомасының 85%-на дейін жетеді (мысалы, шағын және микробизнестің кейбір несиелері үшін). Бұл «кепілсіз несие» емес, соманың бір бөлігіне берілетін кепілдік. | AD6: • Жеке кепіл қамтамасыз етуінің жеткіліксіздігі • Кепілдік берудің нақты тетігінің шарттарына сәйкестік • Қаржыландыруды қаржы ұйымының мақұлдауы | AE6: • Жеке куәлік • ЖК немесе ЖШС тіркеу құжаттары • Бизнес-жоспар және қаржылық есептеулер • Жоба туралы мәліметтер және сатып алынатын мүлікке құжаттар • Кепіл құжаттары (қажет болса) • Алушы санатына сәйкестікті растау | AF6: 1. Банк-серіктеске немесе операторға жүгініп, несиеңіз үшін кепілдіктің қолжетімді екенін нақтылаңыз. 2. Құжаттарды дайындаңыз. 3. Өтінімді оператор көрсеткен тәсілмен беріңіз (шара мен өңірге байланысты). 4. Шешімді күтіңіз. Бас тартылған жағдайда себебін және қайта өтінім беру мүмкіндігін біліңіз. | AG6: кепіл несие банк кепілдік кофехана дүкен салон
A7: «Ауыл аманаты» — микрокредит для села | B7: Сельское микрокредитование | C7: Льготный кредит | D7: Вся РК | E7: Сельское хозяйство | F7: Только село и малые города; животноводство до 7 лет; это кредит, не грант | G7: до 2,5% годовых, срок до 5 лет | I7: https://finance.kz/articles/gosudarstvennye-programmy-podderzhki-predprinimateley | J7: Опубликовано | K7: 46299 | L7: =IF(OR(A7="",H7=""),"",H7-TODAY()) | M7: =IF(A7="","",IF(H7="","Уточняйте",IF(L7<0,"Истёк",IF(L7<=30,"Скоро дедлайн","Открыто")))) -> Уточняйте | N7: ферма фермер село животноводство растениеводство техника кооператив | O7: Льготные микрокредиты для сельского бизнеса и малых городов. Это кредит, а не грант. | P7: • Сельхозпроизводители • Жители села и малых городов • Сельскохозяйственные кооперативы | Q7: Программа развивает предпринимательство на селе. Финансируются животноводство, растениеводство, переработка, закупка техники и оборудования, кооперативы и отдельные несельскохозяйственные направления. Номинальная ставка — не более 2,5% годовых, срок обычно до 5 лет, для животноводства — до 7 лет. Деньги нужно использовать по назначению и вернуть. | R7: • Проект в сельской местности или малом городе • Целевое использование средств • Лимиты и условия зависят от категории проекта и региональных правил | S7: • Удостоверение личности • Регистрационные документы ИП или ТОО • Бизнес-план и финансовые расчёты • Сведения о проекте и документы на приобретаемое имущество • Документы по залогу (если требуются) • Подтверждение соответствия категории получателя | T7: 1. Узнайте региональный порядок подачи: в ряде регионов заявки принимаются в электронном виде. 2. Подготовьте документы. 3. Подайте заявку тем способом, который указан оператором (зависит от меры и региона). 4. Дождитесь решения. При отказе узнайте причину и возможность повторной подачи. | U7: https://finance.kz/articles/gosudarstvennye-programmy-podderzhki-predprinimateley | V7: Нет — добавить | W7: «Ауыл аманаты» — ауылға арналған микронесие | X7: Ауылдық микронесиелеу | Y7: жылдық 2,5%-ға дейін, мерзімі 5 жылға дейін | Z7: Тек ауыл және шағын қалалар; мал шаруашылығы 7 жылға дейін; бұл несие, грант емес | AA7: Ауыл бизнесі мен шағын қалаларға арналған жеңілдетілген микронесиелер. Бұл несие, грант емес. | AB7: • Ауыл шаруашылығы өндірушілері • Ауыл және шағын қала тұрғындары • Ауыл шаруашылығы кооперативтері | AC7: Бағдарлама ауылда кәсіпкерлікті дамытады. Мал шаруашылығы, өсімдік шаруашылығы, қайта өңдеу, техника мен жабдық сатып алу, кооперативтер және ауыл шаруашылығына жатпайтын кейбір бағыттар қаржыландырылады. Номиналды мөлшерлеме — жылдық 2,5%-дан аспайды, мерзімі әдетте 5 жылға дейін, мал шаруашылығы үшін — 7 жылға дейін. Қаражатты мақсатына сай пайдаланып, қайтару қажет. | AD7: • Жоба ауылдық жерде немесе шағын қалада • Қаражатты мақсатты пайдалану • Лимиттер мен шарттар жоба санатына және өңірлік ережелерге байланысты | AE7: • Жеке куәлік • ЖК немесе ЖШС тіркеу құжаттары • Бизнес-жоспар және қаржылық есептеулер • Жоба туралы мәліметтер және сатып алынатын мүлікке құжаттар • Кепіл құжаттары (қажет болса) • Алушы санатына сәйкестікті растау | AF7: 1. Өңірлік өтінім беру тәртібін біліңіз: бірқатар өңірде өтінімдер электронды түрде қабылданады. 2. Құжаттарды дайындаңыз. 3. Өтінімді оператор көрсеткен тәсілмен беріңіз (шара мен өңірге байланысты). 4. Шешімді күтіңіз. Бас тартылған жағдайда себебін және қайта өтінім беру мүмкіндігін біліңіз. | AG7: ферма фермер ауыл мал шаруашылығы өсімдік шаруашылығы техника кооператив ауыл шаруашылығы
A8: Резидентство Astana Hub | B8: Astana Hub | C8: Налоговая льгота | D8: Вся РК | E8: IT | F8: IT-компании; онлайн-регистрация; взнос ≈1% дохода; квартальная отчётность | G8: 0% КПН и НДС по аккредитованной ИКТ-деятельности | I8: https://registration.astanahub.com | J8: Опубликовано | K8: 46299 | L8: =IF(OR(A8="",H8=""),"",H8-TODAY()) | M8: =IF(A8="","",IF(H8="","Уточняйте",IF(L8<0,"Истёк",IF(L8<=30,"Скоро дедлайн","Открыто")))) -> Уточняйте | N8: it стартап разработка программист софт технопарк | O8: Налоговые льготы для IT-компаний по аккредитованным видам ИКТ-деятельности. | P8: • IT-компании (юридические лица) • IT-стартапы | Q8: Резидентам Astana Hub доступен специальный налоговый режим по приоритетным видам ИКТ-деятельности. Ориентировочно: освобождение от КПН и НДС по ИКТ, взнос около 1% дохода, квартальная отчётность. Регистрировать компанию в Астане не требуется. Потеря статуса может повлечь доначисление налогов — соблюдайте условия. | R8: • Юридическое лицо с аккредитованным видом ИКТ-деятельности • Взнос около 1% дохода и квартальная отчётность • Льготы действуют только на доходы от допустимых видов деятельности | S8: • Регистрационные документы компании • Описание деятельности по ИКТ • Остальное — по требованиям онлайн-портала | T8: 1. Проверьте, что ваша деятельность входит в перечень приоритетных видов ИКТ. 2. Подайте онлайн-заявку на портале регистрации. 3. Ориентировочный срок рассмотрения — до 25 рабочих дней. 4. Сдавайте квартальную отчётность. | U8: https://astanahub.com | V8: Да | W8: Astana Hub резиденттігі | X8: Astana Hub | Y8: аккредиттелген АКТ қызметі бойынша КТС және ҚҚС 0% | Z8: IT-компаниялар; онлайн тіркеу; жарна ≈ табыстың 1%; тоқсандық есептілік | AA8: Аккредиттелген АКТ қызмет түрлері бойынша IT-компанияларға арналған салық жеңілдіктері. | AB8: • IT-компаниялар (заңды тұлғалар) • IT-стартаптар | AC8: Astana Hub резиденттеріне АКТ-ның басым қызмет түрлері бойынша арнайы салық режимі қолжетімді. Шамамен: АКТ бойынша КТС және ҚҚС-тан босату, табыстың шамамен 1% көлеміндегі жарна, тоқсандық есептілік. Компанияны Астанада тіркеудің қажеті жоқ. Мәртебені жоғалту салықтардың қосымша есептелуіне әкелуі мүмкін — шарттарды сақтаңыз. | AD8: • Аккредиттелген АКТ қызмет түрі бар заңды тұлға • Табыстың шамамен 1% көлеміндегі жарна және тоқсандық есептілік • Жеңілдіктер тек рұқсат етілген қызмет түрлерінен түсетін табысқа қолданылады | AE8: • Компанияның тіркеу құжаттары • АКТ бойынша қызметтің сипаттамасы • Қалғаны — онлайн-порталдың талаптары бойынша | AF8: 1. Қызметіңіздің АКТ-ның басым түрлерінің тізіміне кіретінін тексеріңіз. 2. Тіркеу порталында онлайн-өтінім беріңіз. 3. Қарау мерзімі шамамен 25 жұмыс күніне дейін. 4. Тоқсандық есептілікті тапсырыңыз. | AG8: it стартап әзірлеу бағдарламашы софт технопарк
A9: Almaty AI Hub | B9: Акимат Алматы | C9: Налоговая льгота | D9: Алматы | E9: IT | F9: Анонсированная площадка для IT; проверьте, запущена ли | G9: налоговые преференции (ожидаются) | I9: https://kapital.kz/tehnology/146124/v-almaty-sozdadut-ai-hub-s-lgotami-dlya-it-kompanij.html | J9: Анонс | K9: 46299 | L9: =IF(OR(A9="",H9=""),"",H9-TODAY()) | M9: =IF(A9="","",IF(H9="","Уточняйте",IF(L9<0,"Истёк",IF(L9<=30,"Скоро дедлайн","Открыто")))) -> Уточняйте | N9: it стартап ai искусственный интеллект | O9: Анонсированная площадка для IT-компаний Алматы по аналогии с Astana Hub. | P9: • IT-компании Алматы • IT-стартапы | Q9: Власти Алматы анонсировали создание Almaty AI Hub, резиденты которого смогут рассчитывать на налоговые преференции. По заявлению представителя города, условия планируются такими же, как в Astana Hub. Проверьте, запущена ли площадка и открыт ли приём заявок. | R9: • Условия пока не опубликованы — следите за анонсами акимата | S9: • Перечень документов появится после запуска | T9: 1. Следите за официальными объявлениями акимата Алматы. 2. После запуска проверьте требования и подайте заявку. | U9: https://kapital.kz/tehnology/146124/v-almaty-sozdadut-ai-hub-s-lgotami-dlya-it-kompanij.html | V9: Нет — добавить
L10: =IF(OR(A10="",H10=""),"",H10-TODAY()) | M10: =IF(A10="","",IF(H10="","Уточняйте",IF(L10<0,"Истёк",IF(L10<=30,"Скоро дедлайн","Открыто"))))
L11: =IF(OR(A11="",H11=""),"",H11-TODAY()) | M11: =IF(A11="","",IF(H11="","Уточняйте",IF(L11<0,"Истёк",IF(L11<=30,"Скоро дедлайн","Открыто"))))
L12: =IF(OR(A12="",H12=""),"",H12-TODAY()) | M12: =IF(A12="","",IF(H12="","Уточняйте",IF(L12<0,"Истёк",IF(L12<=30,"Скоро дедлайн","Открыто"))))
L13: =IF(OR(A13="",H13=""),"",H13-TODAY()) | M13: =IF(A13="","",IF(H13="","Уточняйте",IF(L13<0,"Истёк",IF(L13<=30,"Скоро дедлайн","Открыто"))))
L14: =IF(OR(A14="",H14=""),"",H14-TODAY()) | M14: =IF(A14="","",IF(H14="","Уточняйте",IF(L14<0,"Истёк",IF(L14<=30,"Скоро дедлайн","Открыто"))))
L15: =IF(OR(A15="",H15=""),"",H15-TODAY()) | M15: =IF(A15="","",IF(H15="","Уточняйте",IF(L15<0,"Истёк",IF(L15<=30,"Скоро дедлайн","Открыто"))))
L16: =IF(OR(A16="",H16=""),"",H16-TODAY()) | M16: =IF(A16="","",IF(H16="","Уточняйте",IF(L16<0,"Истёк",IF(L16<=30,"Скоро дедлайн","Открыто"))))
L17: =IF(OR(A17="",H17=""),"",H17-TODAY()) | M17: =IF(A17="","",IF(H17="","Уточняйте",IF(L17<0,"Истёк",IF(L17<=30,"Скоро дедлайн","Открыто"))))
L18: =IF(OR(A18="",H18=""),"",H18-TODAY()) | M18: =IF(A18="","",IF(H18="","Уточняйте",IF(L18<0,"Истёк",IF(L18<=30,"Скоро дедлайн","Открыто"))))
L19: =IF(OR(A19="",H19=""),"",H19-TODAY()) | M19: =IF(A19="","",IF(H19="","Уточняйте",IF(L19<0,"Истёк",IF(L19<=30,"Скоро дедлайн","Открыто"))))
L20: =IF(OR(A20="",H20=""),"",H20-TODAY()) | M20: =IF(A20="","",IF(H20="","Уточняйте",IF(L20<0,"Истёк",IF(L20<=30,"Скоро дедлайн","Открыто"))))
L21: =IF(OR(A21="",H21=""),"",H21-TODAY()) | M21: =IF(A21="","",IF(H21="","Уточняйте",IF(L21<0,"Истёк",IF(L21<=30,"Скоро дедлайн","Открыто"))))
... L51: =IF(OR(A51="",H51=""),"",H51-TODAY()) | M51: =IF(A51="","",IF(H51="","Уточняйте",IF(L51<0,"Истёк",IF(L51<=30,"Скоро дедлайн","Открыто"))))

Sheet Словарь
A1: Категория | B1: Русский (значение в данных) | C1: Қазақша (KK)
A2: Регион | B2: Все регионы | C2: Барлық өңірлер
A3: Регион | B3: Вся РК | C3: Бүкіл ҚР
A4: Регион | B4: Алматы | C4: Алматы
A5: Регион | B5: Астана | C5: Астана
A6: Регион | B6: Шымкент | C6: Шымкент
A7: Регион | B7: Алматинская область | C7: Алматы облысы
A8: Регион | B8: Абайская область | C8: Абай облысы
A9: Регион | B9: Акмолинская область | C9: Ақмола облысы
A10: Регион | B10: Актюбинская область | C10: Ақтөбе облысы
A11: Регион | B11: Атырауская область | C11: Атырау облысы
A12: Регион | B12: Восточно-Казахстанская область | C12: Шығыс Қазақстан облысы
... A36: Тип | B36: Обучение | C36: Оқыту
A38: Переводы значений фильтров. Русские значения должны совпадать с данными на листе «Программы». Новые сфера/тип/регион добавляйте сюда.

Sheet Схема Airtable
A1: Таблица | B1: Поле | C1: Тип поля Airtable | D1: Параметры / заметки
A2: Programs | B2: Название | C2: Single line text | D2: Основное поле
A3: Programs | B3: Оператор | C3: Single line text | D3: Фонд «Даму», акимат, Astana Hub и т.д.
A4: Programs | B4: Тип | C4: Single select | D4: Грант, Субсидия ставки, Гарантия, Льготный кредит, Налоговая льгота, Обучение
A5: Programs | B5: Регион | C5: Multiple select | D5: Вся РК, Алматы, Алматинская область, другие области. Для Алматы показывайте «Алматы» + «Вся РК»
A6: Programs | B6: Сфера | C6: Multiple select | D6: Все сферы, IT, Сельское хозяйство, Производство, Торговля и услуги, Социальное предпринимательство
A7: Programs | B7: Кому подходит / условия | C7: Long text | D7: Категория получателя, ОКЭД, обязательные условия
A8: Programs | B8: Сумма / параметры | C8: Single line text | D8: Сумма в ₸, МРП, ставка или % гарантии
A9: Programs | B9: Дедлайн | C9: Date | D9: Пусто, если приём идёт по объявлениям
A10: Programs | B10: Ссылка | C10: URL | D10: Официальная страница оператора (лучше, чем обзор)
A11: Programs | B11: Статус | C11: Single select | D11: Черновик, Опубликовано, Анонс, Закрыто. В Softr — вид только «Опубликовано»
A12: Programs | B12: Проверено | C12: Date | D12: Показывайте на карточке для доверия
... A16: Subscribers | B16: Сфера | C16: Single select | D16: Для сегментации рассылки
A17: Subscribers | B17: Дата подписки | C17: Created time
A18: Programs | B18: Кратко | C18: Long text | D18: Текст на карточке
A19: Programs | B19: Подходит для | C19: Long text | D19: Список для галочек ✓ на карточке (ИП, ТОО, сельхозпроизводители…)
A20: Programs | B20: Полное описание | C20: Long text | D20: Страница «Подробнее»
A21: Programs | B21: Требования | C21: Long text | D21: Страница «Подробнее»
A22: Programs | B22: Документы | C22: Long text | D22: Страница «Подробнее»
A23: Programs | B23: Как получить | C23: Long text | D23: Шаги заявки
A24: Programs | B24: Официальный сайт | C24: URL | D24: Кнопка «Перейти на официальный сайт →» — сайт госоргана или оператора
A25: Programs | B25: Офиц. сайт проверен? | C25: Checkbox | D25: Если нет — на сайте кнопка «Открыть источник» с предупреждением
A26: Programs | B26: Название (KK) | C26: Single line text | D26: Казахская версия поля; пусто = показывается русский текст
A27: Programs | B27: Оператор (KK) | C27: Single line text | D27: Казахская версия поля; пусто = показывается русский текст
A28: Programs | B28: Сумма / параметры (KK) | C28: Single line text | D28: Казахская версия поля; пусто = показывается русский текст
A29: Programs | B29: Кому подходит / условия (KK) | C29: Single line text | D29: Казахская версия поля; пусто = показывается русский текст
... A36: Programs | B36: Ключевые слова (KK) | C36: Single line text | D36: Казахская версия поля; пусто = показывается русский текст

Sheet План запуска
A1: Час | B1: Задача | C1: Инструмент | D1: План, ч | E1: Статус | F1: Факт, ч
A2: 1 | B2: Создать базу Airtable: Programs и Subscribers | C2: Airtable | D2: 0.5 | E2: Не начато | F2: 0
A3: 1 | B3: Собрать 30–50 программ: Даму, Атамекен, акимат Алматы, Astana Hub, банки; сверить условия с операторами | C3: Исследование | D3: 0.5 | E3: Не начато | F3: 0
A4: 2 | B4: Подключить Airtable к Softr; список с фильтрами «Регион / Сфера / Тип» и поиском | C4: Softr | D4: 0.5 | E4: Не начато | F4: 0
A5: 2 | B5: Страница программы и форма подписки; вид только «Опубликовано» | C5: Softr | D5: 0.25 | E5: Не начато | F5: 0
A6: 2 | B6: Подключить домен (.kz) | C6: Softr / регистратор | D6: 0.25 | E6: Не начато | F6: 0
A7: 3 | B7: Рассылка: Airtable Automation + Mailchimp/Brevo | C7: Airtable, Brevo | D7: 0.5 | E7: Не начато | F7: 0
A8: 3 | B8: Запуск: Telegram/Instagram-чаты предпринимателей Алматы | C8: Соцсети | D8: 0.5 | E8: Не начато | F8: 0
B9: Итого | D9: =SUM(D2:D8) -> 3 | F9: =SUM(F2:F8) -> 0
B10: Выполнено, % | D10: =IF(D9=0,0,F9/D9) -> 0
B11: Задач со статусом «Готово» | D11: =COUNTIF(E2:E8,"Готово") -> 0
B13: Синие ячейки — редактируемые: план часов, статус, фактические часы.

Sheet Метрики
A1: Проверка спроса
A3: Ввод | B3: Значение | C3: Примечание
A4: Уникальные посетители | B4: 0 | C4: Из аналитики сайта
A5: Подписки на рассылку | B5: 0 | C5: Строки в таблице Subscribers
A6: Клики «Подробнее →» | B6: 0 | C6: События в Softr/аналитике
A7: Платные конверсии (рассылка, размещение, заявки партнёрам) | B7: 0 | C7: Любое событие с выручкой
A8: Выручка с одной платной конверсии, ₸ | B8: 0 | C8: Допущение — задайте цену в тенге
A10: Расчёт (формулы)
A11: Показатель | B11: Значение | C11: Логика
A12: Конверсия в подписку | B12: =IF(B4=0,0,B5/B4) -> 0 | C12: Подписки ÷ Посетители
A13: CTR по кнопке «Подробнее» | B13: =IF(B4=0,0,B6/B4) -> 0 | C13: Клики ÷ Посетители
A14: Конверсия в оплату | B14: =IF(B5=0,0,B7/B5) -> 0 | C14: Платные ÷ Подписки
A15: Общая выручка, ₸ | B15: =B7*B8 -> 0 | C15: Платные × выручка с одной
A16: Выручка на посетителя, ₸ | B16: =IF(B4=0,0,B15/B4) -> 0 | C16: Выручка ÷ Посетители
A18: Состояние каталога (из листа «Программы»)
A19: Показатель | B19: Значение | C19: Логика
A20: Всего программ | B20: =COUNTA(Программы!A2:A51) -> 8 | C20: Непустые названия
A21: Опубликовано | B21: =COUNTIF(Программы!J2:J51,"Опубликовано") -> 7 | C21: Статус = Опубликовано
A22: Скоро дедлайн (≤30 дней) | B22: =COUNTIF(Программы!M2:M51,"Скоро дедлайн") -> 0 | C22: Флаг дедлайна
A23: Истёк — закрыть или удалить | B23: =COUNTIF(Программы!M2:M51,"Истёк") -> 0 | C23: Флаг дедлайна
A24: Гранты | B24: =COUNTIF(Программы!C2:C51,"Грант") -> 2 | C24: Тип = Грант
A25: Субсидии ставки | B25: =COUNTIF(Программы!C2:C51,"Субсидия ставки") -> 1 | C25: Тип = Субсидия ставки
A26: Льготные кредиты | B26: =COUNTIF(Программы!C2:C51,"Льготный кредит") -> 1 | C26: Тип = Льготный кредит
A27: Для Алматы (город + вся РК) | B27: =COUNTIF(Программы!D2:D51,"Алматы")+COUNTIF(Программы!D2:D51,"Вся РК") -> 8 | C27: Видимо жителю Алматы
A28: Только специфичные для Алматы | B28: =COUNTIF(Программы!D2:D51,"Алматы") -> 1 | C28: Добавьте больше местных программ
